python_subunit-1.4.5.dist-info/licenses/COPYING
subunit/__init__.py
subunit/_output.py
subunit/_to_disk.py
subunit/chunked.py
subunit/details.py
subunit/filters.py
subunit/progress_model.py
subunit/run.py
subunit/test_results.py
subunit/v2.py
subunit/filter_scripts/__init__.py
subunit/filter_scripts/subunit2csv.py
subunit/filter_scripts/subunit2disk.py
subunit/filter_scripts/subunit2gtk.py
subunit/filter_scripts/subunit2junitxml.py
subunit/filter_scripts/subunit2pyunit.py
subunit/filter_scripts/subunit_1to2.py
subunit/filter_scripts/subunit_2to1.py
subunit/filter_scripts/subunit_filter.py
subunit/filter_scripts/subunit_ls.py
subunit/filter_scripts/subunit_notify.py
subunit/filter_scripts/subunit_output.py
subunit/filter_scripts/subunit_stats.py
subunit/filter_scripts/subunit_tags.py
subunit/filter_scripts/tap2subunit.py
subunit/tests/__init__.py
subunit/tests/sample-script.py
subunit/tests/sample-two-script.py
subunit/tests/test_chunked.py
subunit/tests/test_details.py
subunit/tests/test_filter_to_disk.py
subunit/tests/test_filters.py
subunit/tests/test_output_filter.py
subunit/tests/test_progress_model.py
subunit/tests/test_run.py
subunit/tests/test_subunit_filter.py
subunit/tests/test_subunit_stats.py
subunit/tests/test_subunit_tags.py
subunit/tests/test_tap2subunit.py
subunit/tests/test_test_protocol.py
subunit/tests/test_test_protocol2.py
subunit/tests/test_test_results.py
python_subunit-1.4.5.dist-info/METADATA
python_subunit-1.4.5.dist-info/WHEEL
python_subunit-1.4.5.dist-info/entry_points.txt
python_subunit-1.4.5.dist-info/top_level.txt
python_subunit-1.4.5.dist-info/RECORD
