Metadata-Version: 2.4
Name: python-subunit
Version: 1.4.5
Summary: Python implementation of subunit test streaming protocol
Author-email: Robert Collins <subunit-dev@lists.launchpad.net>
License: Apache-2.0 or BSD
Project-URL: Bug Tracker, https://bugs.launchpad.net/subunit
Project-URL: Homepage, http://launchpad.net/subunit
Project-URL: Source Code, https://github.com/testing-cabal/subunit/
Keywords: python,streaming,test
Classifier: Intended Audience :: Developers
Classifier: Operating System :: OS Independent
Classifier: Programming Language :: Python :: 3.10
Classifier: Programming Language :: Python :: 3.11
Classifier: Programming Language :: Python :: 3.12
Classifier: Programming Language :: Python :: 3.13
Classifier: Programming Language :: Python :: 3.14
Classifier: Programming Language :: Python
Classifier: Topic :: Software Development :: Testing
Requires-Python: >=3.10
License-File: COPYING
Requires-Dist: iso8601
Requires-Dist: testtools>=2.7
Provides-Extra: docs
Requires-Dist: docutils; extra == "docs"
Provides-Extra: test
Requires-Dist: fixtures; extra == "test"
Requires-Dist: hypothesis; extra == "test"
Requires-Dist: testscenarios; extra == "test"
Dynamic: license-file
